{
    "data": [
        {
            "locale": "zh-Hans",
            "data": {
                "label": "Fcitx 5 Lua",
                "dev_team": "Fcitx / Fcitx 5 for Android",
                "rule_contributors": [
                    "WhiredPlanck"
                ],
                "description": "Fcitx 的 Lua 支持。（插件加载模块）",
                "source_link": "https://github.com/fcitx/fcitx5-lua"
            }
        },
        {
            "locale": "en",
            "data": {
                "label": "Fcitx 5 Lua",
                "dev_team": "Fcitx / Fcitx 5 for Android",
                "rule_contributors": [
                    "WhiredPlanck"
                ],
                "description": "Lua support for fcitx. (addon loader module)",
                "source_link": "https://github.com/fcitx/fcitx5-lua"
            }
        }
    ],
    "uuid": "048E2A92-9A21-41BC-A5A2-016192AB1F52"
}